{
  "display": {
    "icon": {
      "id": "warped_fungus_on_a_stick",
      "components": {
        "custom_model_data": 4000101,
        "custom_data": {
          "opendata": {
            "no_override": 1
          }
        }
      }
    },
    "title": "Fluffy Companion",
    "description": "Craft a cat in a bag",
    "frame": "task",
    "show_toast": true,
    "announce_to_chat": true,
    "hidden": true
  },
  "parent": "trifles:interaction_block",
  "criteria": {
    "requirement": {
      "trigger": "inventory_changed",
      "conditions": {
        "items": [
          {
            "items": [
              "warped_fungus_on_a_stick"
            ],
            "components": {
              "custom_data": {
                "trifles": {
                  "type": "pocketcat"
                }
              }
            }
          }
        ]
      }
    }
  }
}
